LICENSE
MANIFEST.in
README.rst
setup.py
claw/__init__.py
claw/__init__.pyc
claw/constants.py
claw/constants.pyc
claw/html_quotations.py
claw/html_quotations.pyc
claw/quotations.py
claw/quotations.pyc
claw/utils.py
claw/utils.pyc
claw.egg-info/PKG-INFO
claw.egg-info/SOURCES.txt
claw.egg-info/dependency_links.txt
claw.egg-info/pbr.json
claw.egg-info/requires.txt
claw.egg-info/top_level.txt
claw.egg-info/zip-safe
claw/signature/__init__.py
claw/signature/__init__.pyc
claw/signature/bruteforce.py
claw/signature/bruteforce.pyc
claw/signature/constants.py
claw/signature/constants.pyc
claw/signature/extraction.pyc
tests/fixtures/__init__.py
tests/signature/__init__.py
tests/signature/bruteforce_test.py