Metadata-Version: 1.0
Name: claw
Version: 1.2.0
Summary: Library to extract message quotations and signatures.
Home-page: https://github.com/tictail/claw
Author: Tictail
Author-email: tech+pip-claw@gmail.com
License: APACHE2
Platform: UNKNOWN
